recnexteval/__init__.py
recnexteval/algorithms/__init__.py
recnexteval/algorithms/base.py
recnexteval/algorithms/baseline/__init__.py
recnexteval/algorithms/baseline/decay_popularity.py
recnexteval/algorithms/baseline/most_popular.py
recnexteval/algorithms/baseline/random.py
recnexteval/algorithms/baseline/recent_popularity.py
recnexteval/algorithms/itemknn/__init__.py
recnexteval/algorithms/itemknn/itemknn.py
recnexteval/algorithms/itemknn/itemknn_incremental.py
recnexteval/algorithms/itemknn/itemknn_incremental_movielens.py
recnexteval/algorithms/itemknn/itemknn_rolling.py
recnexteval/algorithms/itemknn/itemknn_static.py
recnexteval/algorithms/time_aware_item_knn/__init__.py
recnexteval/algorithms/time_aware_item_knn/base.py
recnexteval/algorithms/time_aware_item_knn/decay_functions.py
recnexteval/algorithms/time_aware_item_knn/ding_2005.py
recnexteval/algorithms/time_aware_item_knn/liu_2010.py
recnexteval/algorithms/time_aware_item_knn/similarity_functions.py
recnexteval/algorithms/time_aware_item_knn/top_k.py
recnexteval/algorithms/time_aware_item_knn/utils.py
recnexteval/algorithms/time_aware_item_knn/vaz_2013.py
recnexteval/algorithms/utils.py
recnexteval/datasets/__init__.py
recnexteval/datasets/base.py
recnexteval/datasets/config/__init__.py
recnexteval/datasets/config/amazon.py
recnexteval/datasets/config/base.py
recnexteval/datasets/config/lastfm.py
recnexteval/datasets/config/movielens.py
recnexteval/datasets/config/yelp.py
recnexteval/datasets/datasets/__init__.py
recnexteval/datasets/datasets/amazon.py
recnexteval/datasets/datasets/base.py
recnexteval/datasets/datasets/lastfm.py
recnexteval/datasets/datasets/movielens.py
recnexteval/datasets/datasets/test.py
recnexteval/datasets/datasets/yelp.py
recnexteval/datasets/metadata/__init__.py
recnexteval/datasets/metadata/amazon.py
recnexteval/datasets/metadata/base.py
recnexteval/datasets/metadata/lastfm.py
recnexteval/datasets/metadata/movielens.py
recnexteval/evaluators/__init__.py
recnexteval-0.1.0.dist-info/WHEEL
recnexteval-0.1.0.dist-info/METADATA
recnexteval-0.1.0.dist-info/RECORD
